cast_common/abstractClass.py
cast_common/actionPlan.py
cast_common/aipRestCall.py
cast_common/highlight.py
cast_common/hlRestCall.py
cast_common/logger.py
cast_common/mri.py
cast_common/powerpoint.py
cast_common/restAPI.py
cast_common/util.py
com_castsoftware_uc_python_common_package-1.1.14.dist-info/licenses/LICENSE
com_castsoftware_uc_python_common_package-1.1.14.dist-info/METADATA
com_castsoftware_uc_python_common_package-1.1.14.dist-info/WHEEL
com_castsoftware_uc_python_common_package-1.1.14.dist-info/top_level.txt
com_castsoftware_uc_python_common_package-1.1.14.dist-info/RECORD
